README.md
setup.py
dml/__init__.py
dml/anmm.cpp
dml/base.py
dml/dml_algorithm.py
dml/dml_eig.cpp
dml/dml_plot.py
dml/dml_utils.cpp
dml/dmlmj.cpp
dml/itml.cpp
dml/kda.cpp
dml/knn.py
dml/lda.cpp
dml/ldml.cpp
dml/lmnn.cpp
dml/lsi.cpp
dml/mcml.cpp
dml/multidml_knn.py
dml/nca.cpp
dml/ncmc.cpp
dml/ncmml.cpp
dml/pca.cpp
dml/tune.py
pyDML.egg-info/PKG-INFO
pyDML.egg-info/SOURCES.txt
pyDML.egg-info/dependency_links.txt
pyDML.egg-info/requires.txt
pyDML.egg-info/top_level.txt
test/test1.py
test/test2.py
test/test3.py
test/test4.py
test/test_doc.py
test/testplot.py