Metadata-Version: 1.1
Name: pyDML
Version: 0.0.1b0
Summary: Distance Metric Learning algorithms for Python
Home-page: https://github.com/jlsuarezdiaz/pyDML
Author: Juan Luis Suárez Díaz
Author-email: jlsuarezdiaz@correo.ugr.es
License: UNKNOWN
Keywords: distance metric learning classification neighbors machine optimization
Platform: UNKNOWN
Classifier: Development Status :: 4 - Beta
Classifier: Intended Audience :: Developers
Classifier: Intended Audience :: Information Technology
Classifier: Intended Audience :: Science/Research
Classifier: License :: OSI Approved :: GNU General Public License v3 (GPLv3)
Classifier: Natural Language :: English
Classifier: Operating System :: OS Independent
Classifier: Programming Language :: Python :: 3.6
Classifier: Programming Language :: Python :: Implementation :: CPython
Classifier: Topic :: Scientific/Engineering :: Artificial Intelligence
Classifier: Topic :: Scientific/Engineering :: Information Analysis
Classifier: Topic :: Scientific/Engineering :: Mathematics
